finmcp/__init__.py
finmcp/main.py
finmcp/config/__init__.py
finmcp/config/config_parser.py
finmcp/crawl/__init__.py
finmcp/crawl/crawl4ai_op.py
finmcp/old/__init__.py
finmcp/old/agent/__init__.py
finmcp/old/agent/react_agent_op.py
finmcp/old/agent/react_search_op.py
finmcp/old/crawl/__init__.py
finmcp/old/crawl/extract_long_text_op.py
finmcp/old/deep_research/__init__.py
finmcp/old/deep_research/conduct_research_op.py
finmcp/old/deep_research/dashscope_deep_research_op.py
finmcp/old/deep_research/langchain_deep_research_op.py
finmcp/old/fin_research_v2/__init__.py
finmcp/old/fin_research_v2/analyse_company_op.py
finmcp/old/fin_search/__init__.py
finmcp/old/fin_search/company_factor_op.py
finmcp/old/fin_search/company_operation_op.py
finmcp/old/fin_search/company_segment_factor_op.py
finmcp/old/fin_search/extract_query_op.py
finmcp/old/fin_supply/__init__.py
finmcp/old/fin_supply/akshare_op.py
finmcp/old/fin_supply/extract_entities_code_op.py
finmcp/old/fin_supply/ths_url_op.py
finmcp/old/search/__init__.py
finmcp/old/search/dashscope_search_op.py
finmcp/old/search/execute_code_op.py
finmcp/old/search/mcp_search_op.py
finmcp/old/search/mock_search_op.py
finmcp/old/search/shell_op.py
finmcp/old/search/tavily_search_op.py
finmcp/utils/__init__.py
finmcp/utils/web_utils.py
finmcp-0.1.0.dist-info/licenses/LICENSE
finmcp-0.1.0.dist-info/METADATA
finmcp-0.1.0.dist-info/WHEEL
finmcp-0.1.0.dist-info/entry_points.txt
finmcp-0.1.0.dist-info/top_level.txt
finmcp-0.1.0.dist-info/RECORD
