Metadata-Version: 2.4
Name: finmcp
Version: 0.1.0
Summary: todo
Author-email: "jinli.yl" <jinli.yl@alibaba-inc.com>
License:                                  Apache License
Project-URL: Homepage, https://github.com/flowllm-ai/finmcp
Project-URL: Documentation, https://flowllm-ai.github.io/finmcp/
Project-URL: Repository, https://github.com/flowllm-ai/finmcp
Keywords: fin,mcp
Classifier: Development Status :: 4 - Beta
Classifier: Intended Audience :: Developers
Classifier: Intended Audience :: Science/Research
Classifier: License :: OSI Approved :: Apache Software License
Classifier: Operating System :: OS Independent
Classifier: Programming Language :: Python :: 3
Classifier: Programming Language :: Python :: 3.10
Classifier: Topic :: Scientific/Engineering :: Artificial Intelligence
Classifier: Topic :: Software Development :: Libraries :: Python Modules
Classifier: Topic :: Software Development :: Libraries :: Application Frameworks
Classifier: Typing :: Typed
Requires-Python: >=3.10
License-File: LICENSE
Requires-Dist: akshare>=1.9.0
Requires-Dist: crawl4ai>=0.7.4
Requires-Dist: flowllm>=0.2.0.6
Provides-Extra: dev
Requires-Dist: pytest>=8.4.2; extra == "dev"
Requires-Dist: pytest_asyncio>=1.2.0; extra == "dev"
Requires-Dist: pre-commit; extra == "dev"
Requires-Dist: mkdocs-shadcn; extra == "dev"
Dynamic: license-file
